README.txt
setup.cfg
setup.py
docs/HISTORY.txt
fez/__init__.py
fez.djangothreadlocal.egg-info/PKG-INFO
fez.djangothreadlocal.egg-info/SOURCES.txt
fez.djangothreadlocal.egg-info/dependency_links.txt
fez.djangothreadlocal.egg-info/entry_points.txt
fez.djangothreadlocal.egg-info/namespace_packages.txt
fez.djangothreadlocal.egg-info/not-zip-safe
fez.djangothreadlocal.egg-info/requires.txt
fez.djangothreadlocal.egg-info/top_level.txt
fez/djangothreadlocal/__init__.py
fez/djangothreadlocal/middleware/__init__.py
fez/djangothreadlocal/middleware/threadlocals.py
