Metadata-Version: 1.0
Name: fez.djangothreadlocal
Version: 0.3
Summary: Add the user object to Django threadlocals
Home-page: http://www.fezconsulting.com
Author: Dan Fairs
Author-email: dan@fezconsulting.com
License: MIT
Platform: UNKNOWN
Classifier: Programming Language :: Python
Classifier: Topic :: Software Development :: Libraries :: Python Modules
Classifier: Framework :: Django
Classifier: License :: OSI Approved :: MIT License
